hyperactive_progress_board/__init__.py
hyperactive_progress_board/dashboard_backend.py
hyperactive_progress_board/progress_board.py
hyperactive_progress_board/progress_io.py
hyperactive_progress_board/run_panel.py
hyperactive_progress_board/tmp_files/__init__.py
hyperactive_progress_board/tmp_files/test_model1:b1343b70203243f792de82550c0e5e43.py
hyperactive_progress_board-0.1.0.dist-info/LICENSE
hyperactive_progress_board-0.1.0.dist-info/METADATA
hyperactive_progress_board-0.1.0.dist-info/WHEEL
hyperactive_progress_board-0.1.0.dist-info/top_level.txt
hyperactive_progress_board-0.1.0.dist-info/RECORD
