Metadata-Version: 2.1
Name: hyperactive-progress-board
Version: 0.1.0
Summary: Add on for Hyperactive package to visualize progress of optimization run.
Home-page: https://github.com/SimonBlanke/tabular-data-explorer
Author: Simon Blanke
Author-email: simon.blanke@yahoo.com
License: MIT
Keywords: visualization,data-science
Platform: UNKNOWN
Classifier: Programming Language :: Python :: 3
Classifier: Programming Language :: Python :: 3.5
Classifier: Programming Language :: Python :: 3.6
Classifier: Programming Language :: Python :: 3.7
Classifier: License :: OSI Approved :: MIT License
Classifier: Operating System :: OS Independent
Classifier: Topic :: Scientific/Engineering :: Information Analysis
Classifier: Topic :: Scientific/Engineering :: Mathematics
Classifier: Topic :: Software Development :: Libraries :: Python Modules
Classifier: Intended Audience :: Developers
Classifier: Intended Audience :: Information Technology
Classifier: Intended Audience :: Science/Research
License-File: LICENSE
Requires-Dist: panel
Requires-Dist: numpy
Requires-Dist: pandas
Requires-Dist: tqdm
Requires-Dist: plotly
Requires-Dist: matplotlib
Requires-Dist: simple-data-collector
